{
    "code":0,
    "message":"成功",
    "content":[
        {
            "id":1,
            "subTitle":"空间立体效果图，完美呈现最终效果",
            "title":"设计文章",
            "desc":"室内设计作为一门新兴的学科，尽管还只是近数十年的事，但是人们有意识地对自己生活、生产活动的室内进行安排布置，甚至美化装饰，赋予室内环境以所祈使的气氛，却早巳从人类文明伊始的时期就已存在",
            "url":"../assets/img/sy_img1.jpg"
        },
        {
            "id":2,
            "subTitle":"空间立体效果图，完美呈现最终效果",
            "title":"设计文章",
            "desc":"室内设计作为一门新兴的学科，尽管还只是近数十年的事，但是人们有意识地对自己生活、生产活动的室内进行安排布置，甚至美化装饰，赋予室内环境以所祈使的气氛，却早巳从人类文明伊始的时期就已存在",
            "url":"../assets/img/sy_img1.jpg"
        }
    ]

}